ebmdatalab
tests
